system_hotkey/__init__.py
system_hotkey/keysymdef.py
system_hotkey/system_hotkey.py
system_hotkey/util.py
system_hotkey/xpybutil_keybind.py
system_hotkey-1.0.3.dist-info/DESCRIPTION.rst
system_hotkey-1.0.3.dist-info/METADATA
system_hotkey-1.0.3.dist-info/RECORD
system_hotkey-1.0.3.dist-info/WHEEL
system_hotkey-1.0.3.dist-info/metadata.json
system_hotkey-1.0.3.dist-info/pbr.json
system_hotkey-1.0.3.dist-info/top_level.txt
