Metadata-Version: 2.0
Name: system-hotkey
Version: 1.0.3
Summary: System wide hotkeys
Home-page: https://github.com/timeyyy/system_hotkey
Author: timothy eichler
Author-email: tim_eichler@hotmail.com
License: BSD3
Keywords: hotkeys python3 shortcutkeys shortuct x11 windows
Platform: UNKNOWN
Classifier: Development Status :: 4 - Beta
Classifier: Intended Audience :: Developers
Classifier: Operating System :: OS Independent
Classifier: License :: OSI Approved :: BSD License
Classifier: Programming Language :: Python :: 3
